{
  "rows": {
    "ARC": {
      "TextStyle": "(Font=(FontObject=\"/Script/Engine.Font'/Game/StrikeTheEarth/Fonts/ZenDots-Regular_Font.ZenDots-Regular_Font'\",OutlineSettings=(OutlineSize=1,OutlineColor=(R=0.000000,G=0.000000,B=0.000000,A=0.250000)),TypefaceFontName=\"Default\",Size=35.000000,MonospacedWidth=1.000000),ColorAndOpacity=(SpecifiedColor=(R=0.252063,G=0.243767,B=0.806952,A=1.000000)),ShadowOffset=(X=0.000000,Y=0.000000),ShadowColorAndOpacity=(R=0.000000,G=0.000000,B=0.000000,A=1.000000),SelectedBackgroundColor=(SpecifiedColor=(R=1.000000,G=0.000000,B=1.000000,A=1.000000),ColorUseRule=UseColor_Foreground),HighlightColor=(SpecifiedColor=(R=0.000000,G=0.000000,B=0.000000,A=1.000000)),HighlightShape=(DrawAs=Image,ImageSize=(X=32.000000,Y=32.000000),Margin=(),TintColor=(SpecifiedColor=(R=1.000000,G=1.000000,B=1.000000,A=1.000000)),OutlineSettings=(CornerRadii=(X=0.000000,Y=0.000000,Z=0.000000,W=1.000000),Color=(SpecifiedColor=(R=0.000000,G=0.000000,B=0.000000,A=0.000000)),RoundingType=HalfHeightRadius),UVRegion=(Min=(X=0.000000,Y=0.000000),Max=(X=0.000000,Y=0.000000),bIsValid=False)),StrikeBrush=(DrawAs=Image,ImageSize=(X=32.000000,Y=32.000000),Margin=(),TintColor=(SpecifiedColor=(R=1.000000,G=1.000000,B=1.000000,A=1.000000)),OutlineSettings=(CornerRadii=(X=0.000000,Y=0.000000,Z=0.000000,W=1.000000),Color=(SpecifiedColor=(R=0.000000,G=0.000000,B=0.000000,A=0.000000)),RoundingType=HalfHeightRadius),UVRegion=(Min=(X=0.000000,Y=0.000000),Max=(X=0.000000,Y=0.000000),bIsValid=False)),UnderlineBrush=(DrawAs=Image,ImageSize=(X=32.000000,Y=32.000000),Margin=(),TintColor=(SpecifiedColor=(R=1.000000,G=1.000000,B=1.000000,A=1.000000)),OutlineSettings=(CornerRadii=(X=0.000000,Y=0.000000,Z=0.000000,W=1.000000),Color=(SpecifiedColor=(R=0.000000,G=0.000000,B=0.000000,A=0.000000)),RoundingType=HalfHeightRadius),UVRegion=(Min=(X=0.000000,Y=0.000000),Max=(X=0.000000,Y=0.000000),bIsValid=False)))"
    },
    "Blue": {
      "TextStyle": "(Font=(FontObject=\"/Script/Engine.Font'/Game/StrikeTheEarth/Fonts/OpenSans/OpenSans.OpenSans'\",OutlineSettings=(OutlineSize=1,OutlineColor=(R=0.000000,G=0.000000,B=0.000000,A=0.250000)),TypefaceFontName=\"SemiBold\",Size=30.000000,MonospacedWidth=1.000000),ColorAndOpacity=(SpecifiedColor=(R=0.635417,G=1.000000,B=1.000000,A=1.000000)),ShadowOffset=(X=0.000000,Y=0.000000),ShadowColorAndOpacity=(R=0.000000,G=0.000000,B=0.000000,A=1.000000),SelectedBackgroundColor=(SpecifiedColor=(R=1.000000,G=0.000000,B=1.000000,A=1.000000),ColorUseRule=UseColor_Foreground),HighlightColor=(SpecifiedColor=(R=0.000000,G=0.000000,B=0.000000,A=1.000000)),HighlightShape=(DrawAs=Image,ImageSize=(X=32.000000,Y=32.000000),Margin=(),TintColor=(SpecifiedColor=(R=1.000000,G=1.000000,B=1.000000,A=1.000000)),OutlineSettings=(CornerRadii=(X=0.000000,Y=0.000000,Z=0.000000,W=1.000000),Color=(SpecifiedColor=(R=0.000000,G=0.000000,B=0.000000,A=0.000000)),RoundingType=HalfHeightRadius),UVRegion=(Min=(X=0.000000,Y=0.000000),Max=(X=0.000000,Y=0.000000),bIsValid=False)),StrikeBrush=(DrawAs=Image,ImageSize=(X=32.000000,Y=32.000000),Margin=(),TintColor=(SpecifiedColor=(R=1.000000,G=1.000000,B=1.000000,A=1.000000)),OutlineSettings=(CornerRadii=(X=0.000000,Y=0.000000,Z=0.000000,W=1.000000),Color=(SpecifiedColor=(R=0.000000,G=0.000000,B=0.000000,A=0.000000)),RoundingType=HalfHeightRadius),UVRegion=(Min=(X=0.000000,Y=0.000000),Max=(X=0.000000,Y=0.000000),bIsValid=False)),UnderlineBrush=(DrawAs=Image,ImageSize=(X=32.000000,Y=32.000000),Margin=(),TintColor=(SpecifiedColor=(R=1.000000,G=1.000000,B=1.000000,A=1.000000)),OutlineSettings=(CornerRadii=(X=0.000000,Y=0.000000,Z=0.000000,W=1.000000),Color=(SpecifiedColor=(R=0.000000,G=0.000000,B=0.000000,A=0.000000)),RoundingType=HalfHeightRadius),UVRegion=(Min=(X=0.000000,Y=0.000000),Max=(X=0.000000,Y=0.000000),bIsValid=False)))"
    },
    "BoldItalic": {
      "TextStyle": "(Font=(FontObject=\"/Script/Engine.Font'/Game/StrikeTheEarth/Fonts/OpenSans/OpenSans.OpenSans'\",OutlineSettings=(OutlineSize=1,OutlineColor=(R=0.000000,G=0.000000,B=0.000000,A=0.250000)),TypefaceFontName=\"SemiBoldItalic\",Size=30.000000,MonospacedWidth=1.000000),ColorAndOpacity=(SpecifiedColor=(R=1.000000,G=1.000000,B=1.000000,A=1.000000)),ShadowOffset=(X=0.000000,Y=0.000000),ShadowColorAndOpacity=(R=0.000000,G=0.000000,B=0.000000,A=1.000000),SelectedBackgroundColor=(SpecifiedColor=(R=1.000000,G=0.000000,B=1.000000,A=1.000000),ColorUseRule=UseColor_Foreground),HighlightColor=(SpecifiedColor=(R=0.000000,G=0.000000,B=0.000000,A=1.000000)),HighlightShape=(DrawAs=Image,ImageSize=(X=32.000000,Y=32.000000),Margin=(),TintColor=(SpecifiedColor=(R=1.000000,G=1.000000,B=1.000000,A=1.000000)),OutlineSettings=(CornerRadii=(X=0.000000,Y=0.000000,Z=0.000000,W=1.000000),Color=(SpecifiedColor=(R=0.000000,G=0.000000,B=0.000000,A=0.000000)),RoundingType=HalfHeightRadius),UVRegion=(Min=(X=0.000000,Y=0.000000),Max=(X=0.000000,Y=0.000000),bIsValid=False)),StrikeBrush=(DrawAs=Image,ImageSize=(X=32.000000,Y=32.000000),Margin=(),TintColor=(SpecifiedColor=(R=1.000000,G=1.000000,B=1.000000,A=1.000000)),OutlineSettings=(CornerRadii=(X=0.000000,Y=0.000000,Z=0.000000,W=1.000000),Color=(SpecifiedColor=(R=0.000000,G=0.000000,B=0.000000,A=0.000000)),RoundingType=HalfHeightRadius),UVRegion=(Min=(X=0.000000,Y=0.000000),Max=(X=0.000000,Y=0.000000),bIsValid=False)),UnderlineBrush=(DrawAs=Image,ImageSize=(X=32.000000,Y=32.000000),Margin=(),TintColor=(SpecifiedColor=(R=1.000000,G=1.000000,B=1.000000,A=1.000000)),OutlineSettings=(CornerRadii=(X=0.000000,Y=0.000000,Z=0.000000,W=1.000000),Color=(SpecifiedColor=(R=0.000000,G=0.000000,B=0.000000,A=0.000000)),RoundingType=HalfHeightRadius),UVRegion=(Min=(X=0.000000,Y=0.000000),Max=(X=0.000000,Y=0.000000),bIsValid=False)))"
    },
    "Brown": {
      "TextStyle": "(Font=(FontObject=\"/Script/Engine.Font'/Game/StrikeTheEarth/Fonts/OpenSans/OpenSans.OpenSans'\",OutlineSettings=(OutlineSize=1,OutlineColor=(R=0.000000,G=0.000000,B=0.000000,A=0.250000)),TypefaceFontName=\"SemiBold\",Size=30.000000,MonospacedWidth=1.000000),ColorAndOpacity=(SpecifiedColor=(R=0.385417,G=0.208889,B=0.138509,A=1.000000)),ShadowOffset=(X=0.000000,Y=0.000000),ShadowColorAndOpacity=(R=0.000000,G=0.000000,B=0.000000,A=1.000000),SelectedBackgroundColor=(SpecifiedColor=(R=1.000000,G=0.000000,B=1.000000,A=1.000000),ColorUseRule=UseColor_Foreground),HighlightColor=(SpecifiedColor=(R=0.000000,G=0.000000,B=0.000000,A=1.000000)),HighlightShape=(DrawAs=Image,ImageSize=(X=32.000000,Y=32.000000),Margin=(),TintColor=(SpecifiedColor=(R=1.000000,G=1.000000,B=1.000000,A=1.000000)),OutlineSettings=(CornerRadii=(X=0.000000,Y=0.000000,Z=0.000000,W=1.000000),Color=(SpecifiedColor=(R=0.000000,G=0.000000,B=0.000000,A=0.000000)),RoundingType=HalfHeightRadius),UVRegion=(Min=(X=0.000000,Y=0.000000),Max=(X=0.000000,Y=0.000000),bIsValid=False)),StrikeBrush=(DrawAs=Image,ImageSize=(X=32.000000,Y=32.000000),Margin=(),TintColor=(SpecifiedColor=(R=1.000000,G=1.000000,B=1.000000,A=1.000000)),OutlineSettings=(CornerRadii=(X=0.000000,Y=0.000000,Z=0.000000,W=1.000000),Color=(SpecifiedColor=(R=0.000000,G=0.000000,B=0.000000,A=0.000000)),RoundingType=HalfHeightRadius),UVRegion=(Min=(X=0.000000,Y=0.000000),Max=(X=0.000000,Y=0.000000),bIsValid=False)),UnderlineBrush=(DrawAs=Image,ImageSize=(X=32.000000,Y=32.000000),Margin=(),TintColor=(SpecifiedColor=(R=1.000000,G=1.000000,B=1.000000,A=1.000000)),OutlineSettings=(CornerRadii=(X=0.000000,Y=0.000000,Z=0.000000,W=1.000000),Color=(SpecifiedColor=(R=0.000000,G=0.000000,B=0.000000,A=0.000000)),RoundingType=HalfHeightRadius),UVRegion=(Min=(X=0.000000,Y=0.000000),Max=(X=0.000000,Y=0.000000),bIsValid=False)))"
    },
    "DarkBlue": {
      "TextStyle": "(Font=(FontObject=\"/Script/Engine.Font'/Game/StrikeTheEarth/Fonts/OpenSans/OpenSans.OpenSans'\",OutlineSettings=(OutlineSize=1,OutlineColor=(R=0.000000,G=0.000000,B=0.000000,A=0.250000)),TypefaceFontName=\"SemiBold\",Size=30.000000,MonospacedWidth=1.000000),ColorAndOpacity=(SpecifiedColor=(R=0.380208,G=0.488416,B=1.000000,A=1.000000)),ShadowOffset=(X=0.000000,Y=0.000000),ShadowColorAndOpacity=(R=0.000000,G=0.000000,B=0.000000,A=1.000000),SelectedBackgroundColor=(SpecifiedColor=(R=1.000000,G=0.000000,B=1.000000,A=1.000000),ColorUseRule=UseColor_Foreground),HighlightColor=(SpecifiedColor=(R=0.000000,G=0.000000,B=0.000000,A=1.000000)),HighlightShape=(DrawAs=Image,ImageSize=(X=32.000000,Y=32.000000),Margin=(),TintColor=(SpecifiedColor=(R=1.000000,G=1.000000,B=1.000000,A=1.000000)),OutlineSettings=(CornerRadii=(X=0.000000,Y=0.000000,Z=0.000000,W=1.000000),Color=(SpecifiedColor=(R=0.000000,G=0.000000,B=0.000000,A=0.000000)),RoundingType=HalfHeightRadius),UVRegion=(Min=(X=0.000000,Y=0.000000),Max=(X=0.000000,Y=0.000000),bIsValid=False)),StrikeBrush=(DrawAs=Image,ImageSize=(X=32.000000,Y=32.000000),Margin=(),TintColor=(SpecifiedColor=(R=1.000000,G=1.000000,B=1.000000,A=1.000000)),OutlineSettings=(CornerRadii=(X=0.000000,Y=0.000000,Z=0.000000,W=1.000000),Color=(SpecifiedColor=(R=0.000000,G=0.000000,B=0.000000,A=0.000000)),RoundingType=HalfHeightRadius),UVRegion=(Min=(X=0.000000,Y=0.000000),Max=(X=0.000000,Y=0.000000),bIsValid=False)),UnderlineBrush=(DrawAs=Image,ImageSize=(X=32.000000,Y=32.000000),Margin=(),TintColor=(SpecifiedColor=(R=1.000000,G=1.000000,B=1.000000,A=1.000000)),OutlineSettings=(CornerRadii=(X=0.000000,Y=0.000000,Z=0.000000,W=1.000000),Color=(SpecifiedColor=(R=0.000000,G=0.000000,B=0.000000,A=0.000000)),RoundingType=HalfHeightRadius),UVRegion=(Min=(X=0.000000,Y=0.000000),Max=(X=0.000000,Y=0.000000),bIsValid=False)))"
    },
    "Default": {
      "TextStyle": "(Font=(FontObject=\"/Script/Engine.Font'/Game/StrikeTheEarth/Fonts/OpenSans/OpenSans.OpenSans'\",OutlineSettings=(OutlineSize=1,OutlineColor=(R=0.000000,G=0.000000,B=0.000000,A=0.250000)),TypefaceFontName=\"SemiBold\",Size=30.000000,MonospacedWidth=1.000000),ColorAndOpacity=(SpecifiedColor=(R=1.000000,G=1.000000,B=1.000000,A=1.000000)),ShadowOffset=(X=0.000000,Y=0.000000),ShadowColorAndOpacity=(R=0.000000,G=0.000000,B=0.000000,A=1.000000),SelectedBackgroundColor=(SpecifiedColor=(R=1.000000,G=0.000000,B=1.000000,A=1.000000),ColorUseRule=UseColor_Foreground),HighlightColor=(SpecifiedColor=(R=0.000000,G=0.000000,B=0.000000,A=1.000000)),HighlightShape=(DrawAs=Image,ImageSize=(X=32.000000,Y=32.000000),Margin=(),TintColor=(SpecifiedColor=(R=1.000000,G=1.000000,B=1.000000,A=1.000000)),OutlineSettings=(CornerRadii=(X=0.000000,Y=0.000000,Z=0.000000,W=1.000000),Color=(SpecifiedColor=(R=0.000000,G=0.000000,B=0.000000,A=0.000000)),RoundingType=HalfHeightRadius),UVRegion=(Min=(X=0.000000,Y=0.000000),Max=(X=0.000000,Y=0.000000),bIsValid=False)),StrikeBrush=(DrawAs=Image,ImageSize=(X=32.000000,Y=32.000000),Margin=(),TintColor=(SpecifiedColor=(R=1.000000,G=1.000000,B=1.000000,A=1.000000)),OutlineSettings=(CornerRadii=(X=0.000000,Y=0.000000,Z=0.000000,W=1.000000),Color=(SpecifiedColor=(R=0.000000,G=0.000000,B=0.000000,A=0.000000)),RoundingType=HalfHeightRadius),UVRegion=(Min=(X=0.000000,Y=0.000000),Max=(X=0.000000,Y=0.000000),bIsValid=False)),UnderlineBrush=(DrawAs=Image,ImageSize=(X=32.000000,Y=32.000000),Margin=(),TintColor=(SpecifiedColor=(R=1.000000,G=1.000000,B=1.000000,A=1.000000)),OutlineSettings=(CornerRadii=(X=0.000000,Y=0.000000,Z=0.000000,W=1.000000),Color=(SpecifiedColor=(R=0.000000,G=0.000000,B=0.000000,A=0.000000)),RoundingType=HalfHeightRadius),UVRegion=(Min=(X=0.000000,Y=0.000000),Max=(X=0.000000,Y=0.000000),bIsValid=False)))"
    },
    "Gold": {
      "TextStyle": "(Font=(FontObject=\"/Script/Engine.Font'/Game/StrikeTheEarth/Fonts/OpenSans/OpenSans.OpenSans'\",OutlineSettings=(OutlineSize=1,OutlineColor=(R=0.000000,G=0.000000,B=0.000000,A=0.250000)),TypefaceFontName=\"SemiBold\",Size=30.000000,MonospacedWidth=1.000000),ColorAndOpacity=(SpecifiedColor=(R=1.000000,G=0.748608,B=0.390625,A=1.000000)),ShadowOffset=(X=0.000000,Y=0.000000),ShadowColorAndOpacity=(R=0.000000,G=0.000000,B=0.000000,A=1.000000),SelectedBackgroundColor=(SpecifiedColor=(R=1.000000,G=0.000000,B=1.000000,A=1.000000),ColorUseRule=UseColor_Foreground),HighlightColor=(SpecifiedColor=(R=0.000000,G=0.000000,B=0.000000,A=1.000000)),HighlightShape=(DrawAs=Image,ImageSize=(X=32.000000,Y=32.000000),Margin=(),TintColor=(SpecifiedColor=(R=1.000000,G=1.000000,B=1.000000,A=1.000000)),OutlineSettings=(CornerRadii=(X=0.000000,Y=0.000000,Z=0.000000,W=1.000000),Color=(SpecifiedColor=(R=0.000000,G=0.000000,B=0.000000,A=0.000000)),RoundingType=HalfHeightRadius),UVRegion=(Min=(X=0.000000,Y=0.000000),Max=(X=0.000000,Y=0.000000),bIsValid=False)),StrikeBrush=(DrawAs=Image,ImageSize=(X=32.000000,Y=32.000000),Margin=(),TintColor=(SpecifiedColor=(R=1.000000,G=1.000000,B=1.000000,A=1.000000)),OutlineSettings=(CornerRadii=(X=0.000000,Y=0.000000,Z=0.000000,W=1.000000),Color=(SpecifiedColor=(R=0.000000,G=0.000000,B=0.000000,A=0.000000)),RoundingType=HalfHeightRadius),UVRegion=(Min=(X=0.000000,Y=0.000000),Max=(X=0.000000,Y=0.000000),bIsValid=False)),UnderlineBrush=(DrawAs=Image,ImageSize=(X=32.000000,Y=32.000000),Margin=(),TintColor=(SpecifiedColor=(R=1.000000,G=1.000000,B=1.000000,A=1.000000)),OutlineSettings=(CornerRadii=(X=0.000000,Y=0.000000,Z=0.000000,W=1.000000),Color=(SpecifiedColor=(R=0.000000,G=0.000000,B=0.000000,A=0.000000)),RoundingType=HalfHeightRadius),UVRegion=(Min=(X=0.000000,Y=0.000000),Max=(X=0.000000,Y=0.000000),bIsValid=False)))"
    },
    "Green": {
      "TextStyle": "(Font=(FontObject=\"/Script/Engine.Font'/Game/StrikeTheEarth/Fonts/OpenSans/OpenSans.OpenSans'\",OutlineSettings=(OutlineSize=1,OutlineColor=(R=0.000000,G=0.000000,B=0.000000,A=0.250000)),TypefaceFontName=\"SemiBold\",Size=30.000000,MonospacedWidth=1.000000),ColorAndOpacity=(SpecifiedColor=(R=0.125434,G=0.354167,B=0.127915,A=1.000000)),ShadowOffset=(X=0.000000,Y=0.000000),ShadowColorAndOpacity=(R=0.000000,G=0.000000,B=0.000000,A=1.000000),SelectedBackgroundColor=(SpecifiedColor=(R=1.000000,G=0.000000,B=1.000000,A=1.000000),ColorUseRule=UseColor_Foreground),HighlightColor=(SpecifiedColor=(R=0.000000,G=0.000000,B=0.000000,A=1.000000)),HighlightShape=(DrawAs=Image,ImageSize=(X=32.000000,Y=32.000000),Margin=(),TintColor=(SpecifiedColor=(R=1.000000,G=1.000000,B=1.000000,A=1.000000)),OutlineSettings=(CornerRadii=(X=0.000000,Y=0.000000,Z=0.000000,W=1.000000),Color=(SpecifiedColor=(R=0.000000,G=0.000000,B=0.000000,A=0.000000)),RoundingType=HalfHeightRadius),UVRegion=(Min=(X=0.000000,Y=0.000000),Max=(X=0.000000,Y=0.000000),bIsValid=False)),StrikeBrush=(DrawAs=Image,ImageSize=(X=32.000000,Y=32.000000),Margin=(),TintColor=(SpecifiedColor=(R=1.000000,G=1.000000,B=1.000000,A=1.000000)),OutlineSettings=(CornerRadii=(X=0.000000,Y=0.000000,Z=0.000000,W=1.000000),Color=(SpecifiedColor=(R=0.000000,G=0.000000,B=0.000000,A=0.000000)),RoundingType=HalfHeightRadius),UVRegion=(Min=(X=0.000000,Y=0.000000),Max=(X=0.000000,Y=0.000000),bIsValid=False)),UnderlineBrush=(DrawAs=Image,ImageSize=(X=32.000000,Y=32.000000),Margin=(),TintColor=(SpecifiedColor=(R=1.000000,G=1.000000,B=1.000000,A=1.000000)),OutlineSettings=(CornerRadii=(X=0.000000,Y=0.000000,Z=0.000000,W=1.000000),Color=(SpecifiedColor=(R=0.000000,G=0.000000,B=0.000000,A=0.000000)),RoundingType=HalfHeightRadius),UVRegion=(Min=(X=0.000000,Y=0.000000),Max=(X=0.000000,Y=0.000000),bIsValid=False)))"
    },
    "Maeve": {
      "TextStyle": "(Font=(FontObject=\"/Script/Engine.Font'/Game/StrikeTheEarth/Fonts/OpenSans/OpenSans.OpenSans'\",OutlineSettings=(OutlineSize=1,OutlineColor=(R=0.000000,G=0.000000,B=0.000000,A=0.250000)),TypefaceFontName=\"SemiBold\",Size=30.000000,MonospacedWidth=1.000000),ColorAndOpacity=(SpecifiedColor=(R=0.000000,G=0.000000,B=0.000000,A=1.000000)),ShadowOffset=(X=0.000000,Y=0.000000),ShadowColorAndOpacity=(R=0.000000,G=0.000000,B=0.000000,A=1.000000),SelectedBackgroundColor=(SpecifiedColor=(R=1.000000,G=0.000000,B=1.000000,A=1.000000),ColorUseRule=UseColor_Foreground),HighlightColor=(SpecifiedColor=(R=0.000000,G=0.000000,B=0.000000,A=1.000000)),HighlightShape=(DrawAs=Image,ImageSize=(X=32.000000,Y=32.000000),Margin=(),TintColor=(SpecifiedColor=(R=1.000000,G=1.000000,B=1.000000,A=1.000000)),OutlineSettings=(CornerRadii=(X=0.000000,Y=0.000000,Z=0.000000,W=1.000000),Color=(SpecifiedColor=(R=0.000000,G=0.000000,B=0.000000,A=0.000000)),RoundingType=HalfHeightRadius),UVRegion=(Min=(X=0.000000,Y=0.000000),Max=(X=0.000000,Y=0.000000),bIsValid=False)),StrikeBrush=(DrawAs=Image,ImageSize=(X=32.000000,Y=32.000000),Margin=(),TintColor=(SpecifiedColor=(R=1.000000,G=1.000000,B=1.000000,A=1.000000)),OutlineSettings=(CornerRadii=(X=0.000000,Y=0.000000,Z=0.000000,W=1.000000),Color=(SpecifiedColor=(R=0.000000,G=0.000000,B=0.000000,A=0.000000)),RoundingType=HalfHeightRadius),UVRegion=(Min=(X=0.000000,Y=0.000000),Max=(X=0.000000,Y=0.000000),bIsValid=False)),UnderlineBrush=(DrawAs=Image,ImageSize=(X=32.000000,Y=32.000000),Margin=(),TintColor=(SpecifiedColor=(R=1.000000,G=1.000000,B=1.000000,A=1.000000)),OutlineSettings=(CornerRadii=(X=0.000000,Y=0.000000,Z=0.000000,W=1.000000),Color=(SpecifiedColor=(R=0.000000,G=0.000000,B=0.000000,A=0.000000)),RoundingType=HalfHeightRadius),UVRegion=(Min=(X=0.000000,Y=0.000000),Max=(X=0.000000,Y=0.000000),bIsValid=False)))"
    },
    "Meridian": {
      "TextStyle": "(Font=(FontObject=\"/Script/Engine.Font'/Game/StrikeTheEarth/Fonts/ZenDots-Regular_Font.ZenDots-Regular_Font'\",OutlineSettings=(OutlineSize=1,OutlineColor=(R=0.000000,G=0.000000,B=0.000000,A=0.250000)),TypefaceFontName=\"Default\",Size=75.000000,MonospacedWidth=1.000000),ColorAndOpacity=(SpecifiedColor=(R=0.366253,G=0.768151,B=0.806952,A=1.000000)),ShadowOffset=(X=0.000000,Y=0.000000),ShadowColorAndOpacity=(R=0.000000,G=0.000000,B=0.000000,A=1.000000),SelectedBackgroundColor=(SpecifiedColor=(R=1.000000,G=0.000000,B=1.000000,A=1.000000),ColorUseRule=UseColor_Foreground),HighlightColor=(SpecifiedColor=(R=0.000000,G=0.000000,B=0.000000,A=1.000000)),HighlightShape=(DrawAs=Image,ImageSize=(X=32.000000,Y=32.000000),Margin=(),TintColor=(SpecifiedColor=(R=1.000000,G=1.000000,B=1.000000,A=1.000000)),OutlineSettings=(CornerRadii=(X=0.000000,Y=0.000000,Z=0.000000,W=1.000000),Color=(SpecifiedColor=(R=0.000000,G=0.000000,B=0.000000,A=0.000000)),RoundingType=HalfHeightRadius),UVRegion=(Min=(X=0.000000,Y=0.000000),Max=(X=0.000000,Y=0.000000),bIsValid=False)),StrikeBrush=(DrawAs=Image,ImageSize=(X=32.000000,Y=32.000000),Margin=(),TintColor=(SpecifiedColor=(R=1.000000,G=1.000000,B=1.000000,A=1.000000)),OutlineSettings=(CornerRadii=(X=0.000000,Y=0.000000,Z=0.000000,W=1.000000),Color=(SpecifiedColor=(R=0.000000,G=0.000000,B=0.000000,A=0.000000)),RoundingType=HalfHeightRadius),UVRegion=(Min=(X=0.000000,Y=0.000000),Max=(X=0.000000,Y=0.000000),bIsValid=False)),UnderlineBrush=(DrawAs=Image,ImageSize=(X=32.000000,Y=32.000000),Margin=(),TintColor=(SpecifiedColor=(R=1.000000,G=1.000000,B=1.000000,A=1.000000)),OutlineSettings=(CornerRadii=(X=0.000000,Y=0.000000,Z=0.000000,W=1.000000),Color=(SpecifiedColor=(R=0.000000,G=0.000000,B=0.000000,A=0.000000)),RoundingType=HalfHeightRadius),UVRegion=(Min=(X=0.000000,Y=0.000000),Max=(X=0.000000,Y=0.000000),bIsValid=False)))"
    },
    "Orange": {
      "TextStyle": "(Font=(FontObject=\"/Script/Engine.Font'/Game/StrikeTheEarth/Fonts/OpenSans/OpenSans.OpenSans'\",OutlineSettings=(OutlineSize=1,OutlineColor=(R=0.000000,G=0.000000,B=0.000000,A=0.250000)),TypefaceFontName=\"SemiBold\",Size=30.000000,MonospacedWidth=1.000000),ColorAndOpacity=(SpecifiedColor=(R=0.614583,G=0.217643,B=0.134440,A=1.000000)),ShadowOffset=(X=0.000000,Y=0.000000),ShadowColorAndOpacity=(R=0.000000,G=0.000000,B=0.000000,A=1.000000),SelectedBackgroundColor=(SpecifiedColor=(R=1.000000,G=0.000000,B=1.000000,A=1.000000),ColorUseRule=UseColor_Foreground),HighlightColor=(SpecifiedColor=(R=0.000000,G=0.000000,B=0.000000,A=1.000000)),HighlightShape=(DrawAs=Image,ImageSize=(X=32.000000,Y=32.000000),Margin=(),TintColor=(SpecifiedColor=(R=1.000000,G=1.000000,B=1.000000,A=1.000000)),OutlineSettings=(CornerRadii=(X=0.000000,Y=0.000000,Z=0.000000,W=1.000000),Color=(SpecifiedColor=(R=0.000000,G=0.000000,B=0.000000,A=0.000000)),RoundingType=HalfHeightRadius),UVRegion=(Min=(X=0.000000,Y=0.000000),Max=(X=0.000000,Y=0.000000),bIsValid=False)),StrikeBrush=(DrawAs=Image,ImageSize=(X=32.000000,Y=32.000000),Margin=(),TintColor=(SpecifiedColor=(R=1.000000,G=1.000000,B=1.000000,A=1.000000)),OutlineSettings=(CornerRadii=(X=0.000000,Y=0.000000,Z=0.000000,W=1.000000),Color=(SpecifiedColor=(R=0.000000,G=0.000000,B=0.000000,A=0.000000)),RoundingType=HalfHeightRadius),UVRegion=(Min=(X=0.000000,Y=0.000000),Max=(X=0.000000,Y=0.000000),bIsValid=False)),UnderlineBrush=(DrawAs=Image,ImageSize=(X=32.000000,Y=32.000000),Margin=(),TintColor=(SpecifiedColor=(R=1.000000,G=1.000000,B=1.000000,A=1.000000)),OutlineSettings=(CornerRadii=(X=0.000000,Y=0.000000,Z=0.000000,W=1.000000),Color=(SpecifiedColor=(R=0.000000,G=0.000000,B=0.000000,A=0.000000)),RoundingType=HalfHeightRadius),UVRegion=(Min=(X=0.000000,Y=0.000000),Max=(X=0.000000,Y=0.000000),bIsValid=False)))"
    },
    "Red": {
      "TextStyle": "(Font=(FontObject=\"/Script/Engine.Font'/Game/StrikeTheEarth/Fonts/OpenSans/OpenSans.OpenSans'\",OutlineSettings=(OutlineSize=1,OutlineColor=(R=0.000000,G=0.000000,B=0.000000,A=0.250000)),TypefaceFontName=\"SemiBold\",Size=30.000000,MonospacedWidth=1.000000),ColorAndOpacity=(SpecifiedColor=(R=0.343750,G=0.118164,B=0.120053,A=1.000000)),ShadowOffset=(X=0.000000,Y=0.000000),ShadowColorAndOpacity=(R=0.000000,G=0.000000,B=0.000000,A=1.000000),SelectedBackgroundColor=(SpecifiedColor=(R=1.000000,G=0.000000,B=1.000000,A=1.000000),ColorUseRule=UseColor_Foreground),HighlightColor=(SpecifiedColor=(R=0.000000,G=0.000000,B=0.000000,A=1.000000)),HighlightShape=(DrawAs=Image,ImageSize=(X=32.000000,Y=32.000000),Margin=(),TintColor=(SpecifiedColor=(R=1.000000,G=1.000000,B=1.000000,A=1.000000)),OutlineSettings=(CornerRadii=(X=0.000000,Y=0.000000,Z=0.000000,W=1.000000),Color=(SpecifiedColor=(R=0.000000,G=0.000000,B=0.000000,A=0.000000)),RoundingType=HalfHeightRadius),UVRegion=(Min=(X=0.000000,Y=0.000000),Max=(X=0.000000,Y=0.000000),bIsValid=False)),StrikeBrush=(DrawAs=Image,ImageSize=(X=32.000000,Y=32.000000),Margin=(),TintColor=(SpecifiedColor=(R=1.000000,G=1.000000,B=1.000000,A=1.000000)),OutlineSettings=(CornerRadii=(X=0.000000,Y=0.000000,Z=0.000000,W=1.000000),Color=(SpecifiedColor=(R=0.000000,G=0.000000,B=0.000000,A=0.000000)),RoundingType=HalfHeightRadius),UVRegion=(Min=(X=0.000000,Y=0.000000),Max=(X=0.000000,Y=0.000000),bIsValid=False)),UnderlineBrush=(DrawAs=Image,ImageSize=(X=32.000000,Y=32.000000),Margin=(),TintColor=(SpecifiedColor=(R=1.000000,G=1.000000,B=1.000000,A=1.000000)),OutlineSettings=(CornerRadii=(X=0.000000,Y=0.000000,Z=0.000000,W=1.000000),Color=(SpecifiedColor=(R=0.000000,G=0.000000,B=0.000000,A=0.000000)),RoundingType=HalfHeightRadius),UVRegion=(Min=(X=0.000000,Y=0.000000),Max=(X=0.000000,Y=0.000000),bIsValid=False)))"
    },
    "Yellow": {
      "TextStyle": "(Font=(FontObject=\"/Script/Engine.Font'/Game/StrikeTheEarth/Fonts/OpenSans/OpenSans.OpenSans'\",OutlineSettings=(OutlineSize=1,OutlineColor=(R=0.000000,G=0.000000,B=0.000000,A=0.250000)),TypefaceFontName=\"SemiBold\",Size=30.000000,MonospacedWidth=1.000000),ColorAndOpacity=(SpecifiedColor=(R=0.560807,G=0.614583,B=0.076823,A=1.000000)),ShadowOffset=(X=0.000000,Y=0.000000),ShadowColorAndOpacity=(R=0.000000,G=0.000000,B=0.000000,A=1.000000),SelectedBackgroundColor=(SpecifiedColor=(R=1.000000,G=0.000000,B=1.000000,A=1.000000),ColorUseRule=UseColor_Foreground),HighlightColor=(SpecifiedColor=(R=0.000000,G=0.000000,B=0.000000,A=1.000000)),HighlightShape=(DrawAs=Image,ImageSize=(X=32.000000,Y=32.000000),Margin=(),TintColor=(SpecifiedColor=(R=1.000000,G=1.000000,B=1.000000,A=1.000000)),OutlineSettings=(CornerRadii=(X=0.000000,Y=0.000000,Z=0.000000,W=1.000000),Color=(SpecifiedColor=(R=0.000000,G=0.000000,B=0.000000,A=0.000000)),RoundingType=HalfHeightRadius),UVRegion=(Min=(X=0.000000,Y=0.000000),Max=(X=0.000000,Y=0.000000),bIsValid=False)),StrikeBrush=(DrawAs=Image,ImageSize=(X=32.000000,Y=32.000000),Margin=(),TintColor=(SpecifiedColor=(R=1.000000,G=1.000000,B=1.000000,A=1.000000)),OutlineSettings=(CornerRadii=(X=0.000000,Y=0.000000,Z=0.000000,W=1.000000),Color=(SpecifiedColor=(R=0.000000,G=0.000000,B=0.000000,A=0.000000)),RoundingType=HalfHeightRadius),UVRegion=(Min=(X=0.000000,Y=0.000000),Max=(X=0.000000,Y=0.000000),bIsValid=False)),UnderlineBrush=(DrawAs=Image,ImageSize=(X=32.000000,Y=32.000000),Margin=(),TintColor=(SpecifiedColor=(R=1.000000,G=1.000000,B=1.000000,A=1.000000)),OutlineSettings=(CornerRadii=(X=0.000000,Y=0.000000,Z=0.000000,W=1.000000),Color=(SpecifiedColor=(R=0.000000,G=0.000000,B=0.000000,A=0.000000)),RoundingType=HalfHeightRadius),UVRegion=(Min=(X=0.000000,Y=0.000000),Max=(X=0.000000,Y=0.000000),bIsValid=False)))"
    },
    "Yellow_0": {
      "TextStyle": "(Font=(FontObject=\"/Script/Engine.Font'/Game/StrikeTheEarth/Fonts/OpenSans/OpenSans.OpenSans'\",OutlineSettings=(OutlineSize=1,OutlineColor=(R=0.000000,G=0.000000,B=0.000000,A=0.250000)),TypefaceFontName=\"SemiBold\",Size=30.000000,MonospacedWidth=1.000000),ColorAndOpacity=(SpecifiedColor=(R=0.560807,G=0.614583,B=0.076823,A=1.000000)),ShadowOffset=(X=0.000000,Y=0.000000),ShadowColorAndOpacity=(R=0.000000,G=0.000000,B=0.000000,A=1.000000),SelectedBackgroundColor=(SpecifiedColor=(R=1.000000,G=0.000000,B=1.000000,A=1.000000),ColorUseRule=UseColor_Foreground),HighlightColor=(SpecifiedColor=(R=0.000000,G=0.000000,B=0.000000,A=1.000000)),HighlightShape=(DrawAs=Image,ImageSize=(X=32.000000,Y=32.000000),Margin=(),TintColor=(SpecifiedColor=(R=1.000000,G=1.000000,B=1.000000,A=1.000000)),OutlineSettings=(CornerRadii=(X=0.000000,Y=0.000000,Z=0.000000,W=1.000000),Color=(SpecifiedColor=(R=0.000000,G=0.000000,B=0.000000,A=0.000000)),RoundingType=HalfHeightRadius),UVRegion=(Min=(X=0.000000,Y=0.000000),Max=(X=0.000000,Y=0.000000),bIsValid=False)),StrikeBrush=(DrawAs=Image,ImageSize=(X=32.000000,Y=32.000000),Margin=(),TintColor=(SpecifiedColor=(R=1.000000,G=1.000000,B=1.000000,A=1.000000)),OutlineSettings=(CornerRadii=(X=0.000000,Y=0.000000,Z=0.000000,W=1.000000),Color=(SpecifiedColor=(R=0.000000,G=0.000000,B=0.000000,A=0.000000)),RoundingType=HalfHeightRadius),UVRegion=(Min=(X=0.000000,Y=0.000000),Max=(X=0.000000,Y=0.000000),bIsValid=False)),UnderlineBrush=(DrawAs=Image,ImageSize=(X=32.000000,Y=32.000000),Margin=(),TintColor=(SpecifiedColor=(R=1.000000,G=1.000000,B=1.000000,A=1.000000)),OutlineSettings=(CornerRadii=(X=0.000000,Y=0.000000,Z=0.000000,W=1.000000),Color=(SpecifiedColor=(R=0.000000,G=0.000000,B=0.000000,A=0.000000)),RoundingType=HalfHeightRadius),UVRegion=(Min=(X=0.000000,Y=0.000000),Max=(X=0.000000,Y=0.000000),bIsValid=False)))"
    }
  },
  "table": "DT_IntroTextStyles"
}
